rae_cli-0.2.10.dist-info/licenses/LICENSE
rapid_analytics_engineering/__init__.py
rapid_analytics_engineering/main.py
rapid_analytics_engineering/cli/__init__.py
rapid_analytics_engineering/cli/cli.py
rapid_analytics_engineering/data_modeling/__init__.py
rapid_analytics_engineering/data_modeling/dbt_modeling.py
rapid_analytics_engineering/data_modeling/sql_mesh_modeling.py
rapid_analytics_engineering/data_orchestration/__init__.py
rapid_analytics_engineering/data_orchestration/airflow_orchestration.py
rapid_analytics_engineering/data_orchestration/dagster_orchestration.py
rapid_analytics_engineering/data_storage/__init__.py
rapid_analytics_engineering/data_storage/mysql_storage.py
rapid_analytics_engineering/data_storage/postgresql_storage.py
rapid_analytics_engineering/easter_eggs/__init__.py
rapid_analytics_engineering/easter_eggs/wildflower.py
rapid_analytics_engineering/generators/__init__.py
rapid_analytics_engineering/generators/docker_compose_generator.py
rapid_analytics_engineering/managers/__init__.py
rapid_analytics_engineering/managers/data_modeling_manager.py
rapid_analytics_engineering/managers/data_orchestration_manager.py
rapid_analytics_engineering/managers/data_storage_manager.py
rapid_analytics_engineering/managers/settings_manager.py
rapid_analytics_engineering/utility/__init__.py
rapid_analytics_engineering/utility/base_manager.py
rapid_analytics_engineering/utility/base_tool.py
rapid_analytics_engineering/utility/dockerfile_writer.py
rapid_analytics_engineering/utility/indented_dumper.py
rapid_analytics_engineering/utility/shell_script_writer.py
rapid_analytics_engineering/utility/supported_tools.py
rapid_analytics_engineering/utility/yaml_configs/__init__.py
rae_cli-0.2.10.dist-info/METADATA
rae_cli-0.2.10.dist-info/WHEEL
rae_cli-0.2.10.dist-info/entry_points.txt
rae_cli-0.2.10.dist-info/top_level.txt
rae_cli-0.2.10.dist-info/RECORD
