Metadata-Version: 2.4
Name: rae-cli
Version: 0.2.10
Summary: CLI tool for scaffolding analytics engineering data stacks.
Home-page: https://github.com/CodeBroJim/rae
Author: James Reeves
Author-email: james@codebrojim.com
License: Proprietary
Classifier: Programming Language :: Python :: 3
Classifier: Operating System :: OS Independent
Classifier: License :: Other/Proprietary License
Requires-Python: >=3.8
License-File: LICENSE
Requires-Dist: asciimatics==1.15.0
Requires-Dist: click==8.1.7
Requires-Dist: PyYAML==6.0.2
Requires-Dist: pyfiglet==1.0.2
Requires-Dist: questionary==2.0.1
Requires-Dist: rich==14.0.0
Provides-Extra: dev
Requires-Dist: black==24.10.0; extra == "dev"
Requires-Dist: coverage==7.6.10; extra == "dev"
Requires-Dist: flake8==7.1.1; extra == "dev"
Requires-Dist: isort==5.13.2; extra == "dev"
Requires-Dist: mypy==1.10.0; extra == "dev"
Requires-Dist: nodeenv==1.9.1; extra == "dev"
Requires-Dist: pre_commit==4.2.0; extra == "dev"
Requires-Dist: Pygments==2.19.1; extra == "dev"
Requires-Dist: pytest==8.3.4; extra == "dev"
Requires-Dist: pytest-cov==6.0.0; extra == "dev"
Requires-Dist: pytest-mock==3.14.0; extra == "dev"
Requires-Dist: virtualenv==20.30.0; extra == "dev"
Dynamic: author
Dynamic: author-email
Dynamic: classifier
Dynamic: description
Dynamic: description-content-type
Dynamic: home-page
Dynamic: license
Dynamic: license-file
Dynamic: provides-extra
Dynamic: requires-dist
Dynamic: requires-python
Dynamic: summary
